alhambra/__init__.py
alhambra/anneal.py
alhambra/endreorder.py
alhambra/ends.py
alhambra/fastlatticedefect.py
alhambra/fastreduce.py
alhambra/fastreduceD.py
alhambra/latticedefect.py
alhambra/scripts.py
alhambra/seeds.py
alhambra/sensitivity.py
alhambra/sensitivitynew.py
alhambra/sensitivityprofiles.py
alhambra/seq.py
alhambra/test_seq.py
alhambra/tiles.py
alhambra/tilesets.py
alhambra/tilestructures.py
alhambra/util.py
alhambra/data/rgb.txt
alhambra/peppercomps/tile_adapter_5up.comp
alhambra/peppercomps/tile_adapter_5up_1h.comp
alhambra/peppercomps/tile_adapter_5up_2h.comp
alhambra/peppercomps/tile_daoe_3up.comp
alhambra/peppercomps/tile_daoe_3up_2h.comp
alhambra/peppercomps/tile_daoe_5up.comp
alhambra/peppercomps/tile_daoe_5up_2h.comp
alhambra/peppercomps/tile_daoe_doublehoriz_35up.comp
alhambra/peppercomps/tile_daoe_doublehoriz_35up_1h2i.comp
alhambra/peppercomps/tile_daoe_doublehoriz_35up_2h3h.comp
alhambra/peppercomps/tile_daoe_doublehoriz_35up_3h4h.comp
alhambra/peppercomps/tile_daoe_doublehoriz_35up_4h5b.comp
alhambra/peppercomps/tile_daoe_doublehoriz_35up_4h5i.comp
alhambra/peppercomps/tile_daoe_doublevert_35up_2b3h.comp
alhambra/peppercomps/tile_daoe_doublevert_35up_2h3h.comp
alhambra/peppercomps/tile_daoe_doublevert_35up_4h5h.comp
alhambra/peppercomps-j1/tile_adapter_5up.comp
alhambra/peppercomps-j1/tile_adapter_5up_1h.comp
alhambra/peppercomps-j1/tile_adapter_5up_2h.comp
alhambra/peppercomps-j1/tile_daoe_3up.comp
alhambra/peppercomps-j1/tile_daoe_3up_2h.comp
alhambra/peppercomps-j1/tile_daoe_5up.comp
alhambra/peppercomps-j1/tile_daoe_5up_2h.comp
alhambra/peppercomps-j1/tile_daoe_doublehoriz_35up.comp
alhambra/peppercomps-j1/tile_daoe_doublehoriz_35up_1h2i.comp
alhambra/peppercomps-j1/tile_daoe_doublehoriz_35up_2h3h.comp
alhambra/peppercomps-j1/tile_daoe_doublehoriz_35up_3h4h.comp
alhambra/peppercomps-j1/tile_daoe_doublehoriz_35up_4h5b.comp
alhambra/peppercomps-j1/tile_daoe_doublehoriz_35up_4h5i.comp
alhambra-1.1.0.dist-info/METADATA
alhambra-1.1.0.dist-info/WHEEL
alhambra-1.1.0.dist-info/entry_points.txt
alhambra-1.1.0.dist-info/top_level.txt
alhambra-1.1.0.dist-info/RECORD
