Metadata-Version: 2.1
Name: alhambra
Version: 1.1.0
Summary: DX Tile Set Designer
Home-page: UNKNOWN
Author: Constantine Evans
Author-email: cevans@dna.caltech.edu
License: UNKNOWN
Platform: UNKNOWN
Requires-Dist: numpy
Requires-Dist: stickydesign (>=0.8.1)
Requires-Dist: svgwrite
Requires-Dist: lxml
Requires-Dist: shutilwhich
Requires-Dist: peppercompiler (>=0.1.2)
Requires-Dist: ruamel.yaml (>=0.15.100)
Requires-Dist: cssutils
